gbp_fl-1.1.0.dist-info/METADATA
gbp_fl-1.1.0.dist-info/WHEEL
gbp_fl-1.1.0.dist-info/entry_points.txt
gbp_fl-1.1.0.dist-info/licenses/LICENSE
gbp_fl/__init__.py
gbp_fl/checks.py
gbp_fl/cli/__init__.py
gbp_fl/cli/fetch.py
gbp_fl/cli/ls.py
gbp_fl/cli/search.py
gbp_fl/cli/stats.py
gbp_fl/django/__init__.py
gbp_fl/django/gbp_fl/__init__.py
gbp_fl/django/gbp_fl/apps.py
gbp_fl/django/gbp_fl/migrations/0001_initial.py
gbp_fl/django/gbp_fl/migrations/__init__.py
gbp_fl/django/gbp_fl/models.py
gbp_fl/django/gbp_fl/static/gbp_fl/dashboard.js
gbp_fl/django/gbp_fl/templates/gentoo_build_publisher/dashboard/gbp_fl.html
gbp_fl/django/gbp_fl/templates/gentoo_build_publisher/dashboard/main.html
gbp_fl/django/gbp_fl/templates/gentoo_build_publisher/dashboard/row1.html
gbp_fl/django/gbp_fl/templates/gentoo_build_publisher/machine/buildcard.html
gbp_fl/django/gbp_fl/templatetags/__init__.py
gbp_fl/django/gbp_fl/templatetags/gbp_fl.py
gbp_fl/gateway.py
gbp_fl/graphql/__init__.py
gbp_fl/graphql/binpkg.py
gbp_fl/graphql/content_file.py
gbp_fl/graphql/mutations.py
gbp_fl/graphql/queries.py
gbp_fl/graphql/schema.graphql
gbp_fl/package_utils.py
gbp_fl/py.typed
gbp_fl/queries/list.graphql
gbp_fl/queries/search.graphql
gbp_fl/queries/searchv2.graphql
gbp_fl/queries/stats.graphql
gbp_fl/records/__init__.py
gbp_fl/records/django_orm.py
gbp_fl/records/memory.py
gbp_fl/settings.py
gbp_fl/signals.py
gbp_fl/types.py
gbp_fl/utils.py
gbp_fl/worker/__init__.py
gbp_fl/worker/tasks.py
gbp_fl-1.1.0.dist-info/RECORD
