Metadata-Version: 2.1
Name: gbp-fl
Version: 1.1.0
Summary: pfl-inspired plugin for Gentoo Build Publisher
Author-Email: Albert Hopkins <marduk@letterboxes.org>
License: GPL-3+
Project-URL: homepage, https://github.com/enku/gbp-fl
Project-URL: repository, https://github.com/enku/gbp-fl
Requires-Python: >=3.12
Requires-Dist: gbpcli>=2.4.1
Requires-Dist: yarl>=1.18.3
Requires-Dist: requests>=2.32.3
Requires-Dist: rich>=13.9.4
Provides-Extra: server
Requires-Dist: gentoo-build-publisher>=3.1.0; extra == "server"
Requires-Dist: ariadne>=0.26.0; extra == "server"
